{"833":[{"T":0,"I":["?","?","Educative example","?","????.??.??","*","????.??.??"]},{"T":2,"S":"8/2b5/6R1/7p/7k/5K2/6P1/8"},{"T":1,"M":[{"T":0,"P":["1. Rg6-c6","Bc7-b8"]},{"T":0,"P":["2. Rc6-c4+","Kh4-g5"]},{"T":0,"P":["3. Rc4-d4","Bb8-c7"]},{"T":0,"P":["4. g2-g3","Bc7-b8"]},{"T":0,"P":["5. Rd4-d5+","Kg5-g6"]}]},{"T":2,"S":"1b6/8/6k1/3R3p/8/5KP1/8/8"},{"T":1,"M":[{"T":0,"P":["6. Kf3-g2",""]}]},{"T":2,"S":"1b6/8/6k1/3R3p/8/6P1/6K1/8"}],"839":[{"T":0,"I":["?","?","Troicky","?","1895.??.??","*","1895.??.??"]},{"T":2,"S":"5k2/8/8/2R5/6K1/8/3b2pP/8"},{"T":1,"M":[{"T":0,"P":["1. Rc5-f5+","Kf8-e7"]},{"T":0,"P":["2. Rf5-e5+","Ke7-d6"]},{"T":0,"P":["3. Re5-e1","Bd2xe1"]},{"T":0,"P":["4. Kg4-h3","Ng2-g1=N+"]},{"T":0,"P":["5. Kh3-g2","Ng1-e2"]}]},{"T":2,"S":"8/8/3k4/8/8/8/4n1KP/4b3"},{"T":1,"M":[{"T":0,"P":["6. Kg2-f1",""]}]},{"T":2,"S":"8/8/3k4/8/8/8/4n2P/4bK2"}],"838":[{"T":0,"I":["?","?","Platov V.","?","1906.??.??","*","1906.??.??"]},{"T":2,"S":"8/6P1/8/5p2/1B5K/8/8/2kr4"},{"T":1,"M":[{"T":0,"P":["1. Bb4-d6","Rd1-h1+"]},{"T":0,"P":["2. Bd6-h2","Rh1xh2+"]},{"T":0,"P":["3. Kh4-g3","Rh2-h1"]},{"T":0,"P":["4. Kg3-f2","Rh1-h2+"]},{"T":0,"P":["5. Kf2-f3","Rh2-h3+"]}]},{"T":2,"S":"8/6P1/8/5p2/8/5K1r/8/2k5"},{"T":1,"M":[{"T":0,"P":["6. Kf3-f4","Rh3-h4+"]},{"T":0,"P":["7. Kf4xf5","Rh4-h5+"]},{"T":0,"P":["8. Kf5-f4","Rh5-h4+"]},{"T":0,"P":["9. Kf4-f3","Rh4-h3+"]},{"T":0,"P":["10. Kf3-g2",""]}]},{"T":2,"S":"8/6P1/8/8/8/7r/6K1/2k5"}],"837":[{"T":0,"I":["?","?","Platov V., Platov M","?","1908.??.??","*","1908.??.??"]},{"T":2,"S":"k7/7P/4K3/8/6p1/8/8/r4B2"},{"T":1,"M":[{"T":0,"P":["Ra1-e1+","2. Ke6-d7"]},{"T":0,"P":["Re1-d1+","3. Kd7-c7"]},{"T":0,"P":["Rd1-c1+","4. Bf1-c4"]},{"T":0,"P":["Rc1xc4+","5. Kc7-d7"]},{"T":0,"P":["Rc4-d4+","6. Kd7-e7"]}]},{"T":2,"S":"k7/4K2P/8/8/3r2p1/8/8/8"},{"T":1,"M":[{"T":0,"P":["Rd4-e4+","7. Ke7-f7"]},{"T":0,"P":["Re4-f4+","8. Kf7-g7"]}]},{"T":2,"S":"k7/6KP/8/8/5rp1/8/8/8"}],"836":[{"T":0,"I":["?","?","Szirmai","?","1937.??.??","*","1937.??.??"]},{"T":2,"S":"1k6/2R5/1P6/K7/8/8/2p5/3b4"},{"T":1,"M":[{"T":0,"P":["1. Ka5-b4","Kb8-a8"]},{"T":0,"P":["2. Kb4-a3","Ka8-b8"]},{"T":0,"P":["3. Ka3-a2","Kb8-a8"]},{"T":0,"P":["4. Ka2-b2","Ka8-b8"]},{"T":0,"P":["5. Kb2-a3","Kb8-a8"]}]},{"T":2,"S":"k7/2R5/1P6/8/8/K7/2p5/3b4"},{"T":1,"M":[{"T":0,"P":["6. Ka3-b4","Ka8-b8"]},{"T":0,"P":["7. Kb4-a5","Kb8-a8"]},{"T":0,"P":["8. b6-b7+","Ka8-a7"]},{"T":0,"P":["9. Qb7-b8=Q+","Ka7xb8"]},{"T":0,"P":["10. Ka5-b6","Qc2-c1=Q"]}]},{"T":2,"S":"1k6/2R5/1K6/8/8/8/8/2qb4"},{"T":1,"M":[{"T":0,"P":["11. Rc7xc1","Bd1-b3"]},{"T":0,"P":["12. Rc1-b1",""]}]},{"T":2,"S":"1k6/8/1K6/8/8/1b6/8/1R6"}],"831":[{"T":0,"I":["Australia","?","Ozols","Kalinovsky","1957.??.??","*","1957.??.??"]},{"T":2,"S":"8/8/4pk2/7r/2BP4/3K4/8/8"},{"T":1,"M":[{"T":0,"P":["Kf6-f5","2. Bc4-a2"]},{"T":0,"P":["Rh5-h8","3. Ba2-b3"]},{"T":0,"P":["Rh8-d8","4. Kd3-e3"]}]},{"T":2,"S":"3r4/8/4p3/5k2/3P4/1B2K3/8/8"}],"835":[{"T":0,"I":["?","?","Afanasiev, Dvizov","?","1970.??.??","*","1970.??.??"]},{"T":2,"S":"1b6/4p3/3P4/7R/8/5k2/7K/8"},{"T":1,"M":[{"T":0,"P":["1. Rh5-f5+","Kf3-e4"]},{"T":0,"P":["2. Rf5-f4+","Ke4xf4"]},{"T":0,"P":["3. d6xe7",""]}]},{"T":2,"S":"1b6/4P3/8/8/5k2/8/7K/8"}],"830":[{"T":0,"I":["Puerto Rico","?","De Fotiss","Podgaets","1971.??.??","*","1971.??.??"]},{"T":2,"S":"8/B7/4k3/5p2/8/3r2P1/6K1/8"},{"T":1,"M":[{"T":0,"P":["Ke6-d5","2. Ba7-b8"]},{"T":0,"P":["Kd5-e4","3. Bb8-f4"]},{"T":0,"P":["Rd3-d7","4. Bf4-h6"]},{"T":0,"P":["Rd7-c7","5. Bh6-f4"]},{"T":0,"P":["Rc7-c8","6. Bf4-d6"]}]},{"T":2,"S":"2r5/8/3B4/5p2/4k3/6P1/6K1/8"},{"T":1,"M":[{"T":0,"P":["Rc8-c2+","7. Kg2-h3"]},{"T":0,"P":["Ke4-f3","8. Kh3-h4"]},{"T":0,"P":["Rc2-c6","9. Bd6-f4"]},{"T":0,"P":["Rc6-g6","10. Kh4-h3"]},{"T":0,"P":["Rg6-g7","11. Kh3-h2"]}]},{"T":2,"S":"8/6r1/8/5p2/5B2/5kP1/7K/8"},{"T":1,"M":[{"T":0,"P":["Rg7-h7+","12. Kh2-g1"]},{"T":0,"P":["Rh7-h3",""]}]},{"T":2,"S":"8/8/8/5p2/5B2/5kPr/8/6K1"}],"832":[{"T":0,"I":["New York","?","Keene","Henley","1981.??.??","*","1981.??.??"]},{"T":2,"S":"8/4K3/4p3/3k4/3P1B2/8/8/4r3"},{"T":1,"M":[{"T":0,"P":["1. Bf4-g5","Re1-a1"]},{"T":0,"P":["2. Bg5-f6","Ra1-a7+"]},{"T":0,"P":["3. Ke7-e8","Ra7-h7"]},{"T":0,"P":["4. Ke8-f8","Kd5-e4"]},{"T":0,"P":["5. Kf8-e8","Rh7-b7"]}]},{"T":2,"S":"4K3/1r6/4pB2/8/3Pk3/8/8/8"},{"T":1,"M":[{"T":0,"P":["6. Ke8-d8","Ke4-f5"]},{"T":0,"P":["7. Bf6-h4","Rb7-b4"]},{"T":0,"P":["8. Bh4-f2","Kf5-e4"]},{"T":0,"P":["9. Kd8-d7","Ke4-d5"]},{"T":0,"P":["10. Kd7-e7","Rb4-b7+"]}]},{"T":2,"S":"8/1r2K3/4p3/3k4/3P4/8/5B2/8"},{"T":1,"M":[{"T":0,"P":["11. Ke7-f6","Rb7-b2"]},{"T":0,"P":["12. Bf2-g1","Rb2-b1"]},{"T":0,"P":["13. Bg1-h2","Rb1-d1"]},{"T":0,"P":["14. Bh2-e5","Rd1-e1"]},{"T":0,"P":["15. Be5-g3","Re1-e2"]}]},{"T":2,"S":"8/8/4pK2/3k4/3P4/6B1/4r3/8"},{"T":1,"M":[{"T":0,"P":["16. Bg3-b8",""]}]},{"T":2,"S":"1B6/8/4pK2/3k4/3P4/8/4r3/8"}],"834":[{"T":0,"I":["Brussels","?","Korchnoi","Speelman","1985.??.??","*","1985.??.??"]},{"T":2,"S":"8/8/5p2/4b3/4K1k1/5R2/6P1/8"},{"T":1,"M":[{"T":0,"P":["1. Rf3-h3","Be5-f4"]},{"T":0,"P":["2. Ke4-d4","Bf4-e5+"]},{"T":0,"P":["3. Kd4-e3","Be5-f4+"]},{"T":0,"P":["4. Ke3-e4","Bf4-g5"]},{"T":0,"P":["5. Ke4-d5","Bg5-f4"]}]},{"T":2,"S":"8/8/5p2/3K4/5bk1/7R/6P1/8"},{"T":1,"M":[{"T":0,"P":["6. Kd5-e6","Bf4-e5"]},{"T":0,"P":["7. Rh3-h8","Kg4-g3"]},{"T":0,"P":["8. Rh8-g8+","Kg3-f4"]},{"T":0,"P":["9. Rg8-g7","Be5-b8"]},{"T":0,"P":["10. Rg7-g6","Bb8-e5"]}]},{"T":2,"S":"8/8/4KpR1/4b3/5k2/8/6P1/8"},{"T":1,"M":[{"T":0,"P":["11. Rg6-g8","Be5-c3"]},{"T":0,"P":["12. g2-g3+","Kf4-e4"]},{"T":0,"P":["13. Rg8-g4+","Ke4-f3"]},{"T":0,"P":["14. Rg4-c4","Bc3-d2"]},{"T":0,"P":["15. g3-g4","Bd2-g5"]}]},{"T":2,"S":"8/8/4Kp2/6b1/2R3P1/5k2/8/8"},{"T":1,"M":[{"T":0,"P":["16. Ke6-f5","Kf3-g3"]},{"T":0,"P":["17. Rc4-c8","Bg5-d2"]},{"T":0,"P":["18. Rc8-g8","Bd2-c3"]},{"T":0,"P":["19. Rg8-d8","Kg3-h4"]},{"T":0,"P":["20. Rd8-d3","Bc3-b2"]}]},{"T":2,"S":"8/8/5p2/5K2/6Pk/3R4/1b6/8"},{"T":1,"M":[{"T":0,"P":["21. Rd3-d1","Bb2-c3"]},{"T":0,"P":["22. Rd1-h1+","Kh4-g3"]},{"T":0,"P":["23. Rh1-c1","Bc3-b2"]},{"T":0,"P":["24. Rc1-c2","Bb2-d4"]},{"T":0,"P":["25. Rc2-d2","Bd4-c5"]}]},{"T":2,"S":"8/8/5p2/2b2K2/6P1/6k1/3R4/8"},{"T":1,"M":[{"T":0,"P":["26. Rd2-d5","Bc5-e7"]},{"T":0,"P":["27. Rd5-d3+","Kg3-h4"]},{"T":0,"P":["28. Rd3-d4","Kh4-g3"]},{"T":0,"P":["29. Kf5-e6",""]}]},{"T":2,"S":"8/4b3/4Kp2/8/3R2P1/6k1/8/8"}]}