{"776":[{"T":0,"I":["Netherlands","?","Euwe","Olland","1921.??.??","*","1921.??.??"]},{"T":2,"S":"8/6pp/1p1k4/p7/2PK4/1P6/P4PP1/8"},{"T":1,"M":[{"T":0,"P":["1. a2-a3","h7-h5"]},{"T":0,"P":["2. b3-b4","g7-g5"]},{"T":0,"P":["3. b4xa5","b6xa5"]},{"T":0,"P":["4. c4-c5+","Kd6-c6"]},{"T":0,"P":["5. a3-a4","h5-h4"]}]},{"T":2,"S":"8/8/2k5/p1P3p1/P2K3p/8/5PP1/8"},{"T":1,"M":[{"T":0,"P":["6. f2-f3","Kc6-c7"]},{"T":0,"P":["7. Kd4-d5","Kc7-d7"]},{"T":0,"P":["8. c5-c6+","Kd7-c7"]},{"T":0,"P":["9. Kd5-c5","Kc7-c8"]},{"T":0,"P":["10. Kc5-b6","Kc8-b8"]}]},{"T":2,"S":"1k6/8/1KP5/p5p1/P6p/5P2/6P1/8"},{"T":1,"M":[{"T":0,"P":["11. Kb6xa5",""]}]},{"T":2,"S":"1k6/8/2P5/K5p1/P6p/5P2/6P1/8"}],"770":[{"T":0,"I":["Deutsche Schachblatter","?","Post","?","1941.??.??","*","1941.??.??"]},{"T":2,"S":"8/kp6/3p2p1/p1p5/P1P1P2K/5P2/8/8"},{"T":1,"M":[{"T":0,"P":["1. Kh4-g5","b7-b6"]},{"T":0,"P":["2. Kg5-g4","Ka7-b7"]},{"T":0,"P":["3. f3-f4","Kb7-c6"]},{"T":0,"P":["4. f4-f5","g6xf5+"]},{"T":0,"P":["5. e4xf5","Kc6-d7"]}]},{"T":2,"S":"8/3k4/1p1p4/p1p2P2/P1P3K1/8/8/8"},{"T":1,"M":[{"T":0,"P":["6. f5-f6","Kd7-e6"]},{"T":0,"P":["7. Kg4-g5","Ke6-f7"]},{"T":0,"P":["8. Kg5-f5","Kf7-f8"]},{"T":0,"P":["9. Kf5-e6","Kf8-e8"]},{"T":0,"P":["10. f6-f7+","Ke8-f8"]}]},{"T":2,"S":"5k2/5P2/1p1pK3/p1p5/P1P5/8/8/8"},{"T":1,"M":[{"T":0,"P":["11. Ke6-f6",""]}]},{"T":2,"S":"5k2/5P2/1p1p1K2/p1p5/P1P5/8/8/8"}],"771":[{"T":0,"I":["Deutsche Schachzeitung","?","Wotawa","?","1962.??.??","*","1962.??.??"]},{"T":2,"S":"8/2p2p2/3p3p/4P1pP/8/6PK/1k3P2/8"},{"T":1,"M":[{"T":0,"P":["1. e5-e6","f7xe6"]},{"T":0,"P":["2. f2-f4","g5-g4+"]},{"T":0,"P":["3. Kh3-h4","c7-c5"]},{"T":0,"P":["4. f4-f5","c5-c4"]},{"T":0,"P":["5. f5xe6","c4-c3"]}]},{"T":2,"S":"8/8/3pP2p/7P/6pK/2p3P1/1k6/8"},{"T":1,"M":[{"T":0,"P":["6. e6-e7","c3-c2"]},{"T":0,"P":["7. Qe7-e8=Q","Qc2-c1=Q"]},{"T":0,"P":["8. Qe8-b5+","Kb2-a2"]},{"T":0,"P":["9. Qb5-c4+","Qc1xc4"]}]},{"T":2,"S":"8/8/3p3p/7P/2q3pK/6P1/k7/8"}],"775":[{"T":0,"I":["Italia","?","Bacchelli","Calapso","1967.??.??","*","1967.??.??"]},{"T":2,"S":"8/8/3k4/2p1p3/pp2Pp2/P2K1P2/1P6/8"},{"T":1,"M":[{"T":0,"P":["b4-b3","2. Kd3-c3"]},{"T":0,"P":["Kd6-c7","3. Kc3-d3"]},{"T":0,"P":["Kc7-b6","4. Kd3-c3"]},{"T":0,"P":["Kb6-b5","5. Kc3-d3"]},{"T":0,"P":["c5-c4+","6. Kd3-d2"]}]},{"T":2,"S":"8/8/8/1k2p3/p1p1Pp2/Pp3P2/1P1K4/8"},{"T":1,"M":[{"T":0,"P":["Kb5-c6","7. Kd2-c1"]},{"T":0,"P":["Kc6-c5","8. Kc1-d1"]},{"T":0,"P":["Kc5-d4","9. Kd1-d2"]},{"T":0,"P":["c4-c3+","10. b2xc3+"]},{"T":0,"P":["Kd4-c4",""]}]},{"T":2,"S":"8/8/8/4p3/p1k1Pp2/PpP2P2/3K4/8"}],"777":[{"T":0,"I":["Yugoslavia","?","Cebalo","Zivkovic","1968.??.??","*","1968.??.??"]},{"T":2,"S":"6k1/5p1p/6p1/1p4P1/p6P/P1K5/1P6/8"},{"T":1,"M":[{"T":0,"P":["f7-f5","2. g5xf6"]},{"T":0,"P":["Kg8-f7","3. Kc3-b4"]},{"T":0,"P":["h7-h5","4. Kb4xb5"]},{"T":0,"P":["g6-g5","5. Kb5xa4"]},{"T":0,"P":["g5-g4","6. b2-b4"]}]},{"T":2,"S":"8/5k2/5P2/7p/KP4pP/P7/8/8"},{"T":1,"M":[{"T":0,"P":["g4-g3",""]}]},{"T":2,"S":"8/5k2/5P2/7p/KP5P/P5p1/8/8"}],"779":[{"T":0,"I":["Siegen","?","Bouaziz","Pomar","1970.??.??","*","1970.??.??"]},{"T":2,"S":"8/p7/4k1P1/1p1p3P/1P2pK2/2P5/P7/8"},{"T":1,"M":[{"T":0,"P":["1. h5-h6","Ke6-f6"]},{"T":0,"P":["2. h6-h7","Kf6-g7"]},{"T":0,"P":["3. Kf4-g4","Kg7-h8"]},{"T":0,"P":["4. Kg4-f5","Kh8-g7"]},{"T":0,"P":["5. Kf5-e6","e4-e3"]}]},{"T":2,"S":"8/p5kP/4K1P1/1p1p4/1P6/2P1p3/P7/8"},{"T":1,"M":[{"T":0,"P":["6. Qh7-h8=Q+","Kg7xh8"]},{"T":0,"P":["7. Ke6-f7",""]}]},{"T":2,"S":"7k/p4K2/6P1/1p1p4/1P6/2P1p3/P7/8"}],"773":[{"T":0,"I":["USSR","?","Ozolinia","Sedleniece","1972.??.??","*","1972.??.??"]},{"T":2,"S":"2k5/2P5/1P6/4pp2/6pp/8/4KPPP/8"},{"T":1,"M":[{"T":0,"P":["1. Ke2-e3","f5-f4+"]},{"T":0,"P":["2. Ke3-e4","Kc8-d7"]},{"T":0,"P":["3. f2-f3","h4-h3"]},{"T":0,"P":["4. g2xh3","g4-g3"]},{"T":0,"P":["5. h2xg3","f4xg3"]}]},{"T":2,"S":"8/2Pk4/1P6/4p3/4K3/5PpP/8/8"},{"T":1,"M":[{"T":0,"P":["6. Ke4-e3",""]}]},{"T":2,"S":"8/2Pk4/1P6/4p3/8/4KPpP/8/8"}],"774":[{"T":0,"I":["Tientiste","?","Van der Sterren","Calle","1975.??.??","*","1975.??.??"]},{"T":2,"S":"8/8/7p/2p1k3/1p1p2P1/1P1K1P2/P6P/8"},{"T":1,"M":[{"T":0,"P":["1. h2-h4","Ke5-f4"]},{"T":0,"P":["2. Kd3-d2","Kf4-e5"]},{"T":0,"P":["3. Kd2-e2","Ke5-f4"]},{"T":0,"P":["4. h4-h5","Kf4-g5"]},{"T":0,"P":["5. Ke2-f1","Kg5-f4"]}]},{"T":2,"S":"8/8/7p/2p4P/1p1p1kP1/1P3P2/P7/5K2"},{"T":1,"M":[{"T":0,"P":["6. Kf1-f2","Kf4-g5"]},{"T":0,"P":["7. Kf2-g3","Kg5-f6"]},{"T":0,"P":["8. Kg3-f4","Kf6-e6"]},{"T":0,"P":["9. Kf4-e4","Ke6-f7"]},{"T":0,"P":["10. f3-f4","Kf7-f6"]}]},{"T":2,"S":"8/8/5k1p/2p4P/1p1pKPP1/1P6/P7/8"},{"T":1,"M":[{"T":0,"P":["11. Ke4-f3","Kf6-e6"]},{"T":0,"P":["12. g4-g5","Ke6-f5"]},{"T":0,"P":["13. g5-g6","Kf5-f6"]},{"T":0,"P":["14. f4-f5","Kf6-g7"]},{"T":0,"P":["15. Kf3-e4","Kg7-f6"]}]},{"T":2,"S":"8/8/5kPp/2p2P1P/1p1pK3/1P6/P7/8"},{"T":1,"M":[{"T":0,"P":["16. Ke4-f4","Kf6-g7"]},{"T":0,"P":["17. Kf4-e5","d4-d3"]},{"T":0,"P":["18. f5-f6+",""]}]},{"T":2,"S":"8/6k1/5PPp/2p1K2P/1p6/1P1p4/P7/8"}],"778":[{"T":0,"I":["USSR","?","Ramane","Lopatina","1978.??.??","*","1978.??.??"]},{"T":2,"S":"3k4/4p3/1p4p1/p3Kp2/P6P/1P4P1/8/8"},{"T":1,"M":[{"T":0,"P":["Kd8-d7","2. h4-h5"]},{"T":0,"P":["g6xh5","3. Ke5xf5"]},{"T":0,"P":["Kd7-d6","4. Kf5-g5"]},{"T":0,"P":["e7-e5","5. Kg5xh5"]},{"T":0,"P":["e5-e4","6. Kh5-g4"]}]},{"T":2,"S":"8/8/1p1k4/p7/P3p1K1/1P4P1/8/8"},{"T":1,"M":[{"T":0,"P":["Kd6-e5","7. Kg4-h3"]},{"T":0,"P":["Ke5-d4",""]}]},{"T":2,"S":"8/8/1p6/p7/P2kp3/1P4PK/8/8"}],"772":[{"T":0,"I":["Schach","?","Evreinov","?","1980.??.??","*","1980.??.??"]},{"T":2,"S":"8/2p5/1p1p1p2/3Pk1p1/P1P5/1P3K2/8/8"},{"T":1,"M":[{"T":0,"P":["1. b3-b4","Ke5-d4"]},{"T":0,"P":["2. a4-a5","b6xa5"]},{"T":0,"P":["3. b4xa5","Kd4-c5"]},{"T":0,"P":["4. Kf3-g4","c7-c6"]},{"T":0,"P":["5. a5-a6","Kc5-b6"]}]},{"T":2,"S":"8/8/Pkpp1p2/3P2p1/2P3K1/8/8/8"},{"T":1,"M":[{"T":0,"P":["6. c4-c5+","Kb6xa6"]},{"T":0,"P":["7. c5xd6","Ka6-b6"]},{"T":0,"P":["8. d6-d7","Kb6-c7"]},{"T":0,"P":["9. d5xc6","Kc7-d8"]},{"T":0,"P":["10. Kg4-f5","Kd8-e7"]}]},{"T":2,"S":"8/3Pk3/2P2p2/5Kp1/8/8/8/8"},{"T":1,"M":[{"T":0,"P":["11. Kf5-e4","g5-g4"]},{"T":0,"P":["12. Ke4-e3","f6-f5"]},{"T":0,"P":["13. Ke3-f4","Ke7-d8"]},{"T":0,"P":["14. Kf4xf5","g4-g3"]},{"T":0,"P":["15. Kf5-e6","g3-g2"]}]},{"T":2,"S":"3k4/3P4/2P1K3/8/8/8/6p1/8"},{"T":1,"M":[{"T":0,"P":["16. Ke6-d6",""]}]},{"T":2,"S":"3k4/3P4/2PK4/8/8/8/6p1/8"}]}